zulmorph/__init__.py
zulmorph/__main__.py
zulmorph/zulmorph.py
zulmorph/res/zul.fom
zulmorph-1.0.5.dist-info/licenses/LICENSE
zulmorph-1.0.5.dist-info/METADATA
zulmorph-1.0.5.dist-info/WHEEL
zulmorph-1.0.5.dist-info/entry_points.txt
zulmorph-1.0.5.dist-info/top_level.txt
zulmorph-1.0.5.dist-info/RECORD
