Metadata-Version: 2.4
Name: zulmorph
Version: 1.0.5
Summary: Morphological analysis using ZulMorph
Author-email: Laurette Pretorius and Sonja Bosch <lpretorius@sun.ac.za>, Laurette Pretorius <lpretorius@sun.ac.za>, Sonja Bosch <seb@hbosch.com>
Maintainer-email: Laurette Pretorius <laurette@acm.com>
License: 
Project-URL: Demo, https://portal.sadilar.org/FiniteState/demo/zulmorph/
Keywords: morphological analyzer,foma
Classifier: License :: OSI Approved :: Apache Software License
Classifier: Programming Language :: Python
Classifier: Programming Language :: Python :: 3
License-File: LICENSE
Requires-Dist: foma>=1.0.0
Dynamic: license-file
